microengine_utils/__init__.py
microengine_utils/config.py
microengine_utils/constants.py
microengine_utils/datadog.py
microengine_utils/errors.py
microengine_utils/filesystem.py
microengine_utils/malwarerepoclient.py
microengine_utils/scanner.py
microengine_utils-1.6.1.dist-info/licenses/LICENSE
microengine_utils-1.6.1.dist-info/METADATA
microengine_utils-1.6.1.dist-info/WHEEL
microengine_utils-1.6.1.dist-info/top_level.txt
microengine_utils-1.6.1.dist-info/RECORD
