Metadata-Version: 2.4
Name: microengine-utils
Version: 1.6.1
Summary: Library for Polyswarm Microengine Utility Package
Author-email: PolySwarm Developers <info@polyswarm.io>
License-Expression: MIT
Project-URL: Homepage, https://github.com/polyswarm/microengine-utils
Classifier: Intended Audience :: Developers
Classifier: Operating System :: OS Independent
Classifier: Programming Language :: Python :: 3.10
Classifier: Programming Language :: Python :: 3.11
Classifier: Programming Language :: Python :: 3.12
Classifier: Programming Language :: Python :: 3.13
Classifier: Programming Language :: Python :: Implementation :: PyPy
Requires-Python: <4,>=3.10
License-File: LICENSE
Requires-Dist: datadog>=0.36.0
Requires-Dist: polyswarm-artifact>=2.2
Requires-Dist: pydantic>=2.0
Requires-Dist: requests>=2.32.0
Provides-Extra: tests
Requires-Dist: pytest>=8.4.0; extra == "tests"
Provides-Extra: content-type
Requires-Dist: puremagic; extra == "content-type"
Dynamic: license-file
